euma/__init__.py
euma/palette.py
euma/theme.py
euma/tokens.py
euma-2.0.2.dist-info/licenses/LICENSE
euma-2.0.2.dist-info/WHEEL
euma-2.0.2.dist-info/METADATA
euma-2.0.2.dist-info/RECORD
