Metadata-Version: 2.4
Name: euma
Version: 2.0.2
Summary: Euma, a color and design theme
Keywords: theme,colors,design-tokens
Author-email: Leonhard Maier <git@39z.de>
Maintainer-email: Leonhard Maier <git@39z.de>
License-Expression: MIT
Classifier: Programming Language :: Python :: 3
Classifier: Operating System :: OS Independent
Classifier: Topic :: Multimedia :: Graphics
Classifier: Topic :: Software Development :: User Interfaces
Classifier: Typing :: Typed
Classifier: Topic :: Artistic Software
License-File: LICENSE
Project-URL: homepage, https://39zde.codeberg.page/euma/@main/.codeberg/webpage/dist/index.html
Project-URL: issues, https://codeberg.org/39zde/euma/issues
Project-URL: repository, https://codeberg.org/39zde/euma.git
